rci/__about__.py
rci/__init__.py
rci/__main__.py
rci/_version.py
rci/improved.py
rci/logic/__init__.py
rci/logic/entity.py
rci/logic/listener.py
rci/logic/entities/__init__.py
rci/logic/entities/keyword.py
rci/logic/entities/suite.py
rci/logic/entities/test.py
rci/logic/listeners/__init__.py
rci/logic/listeners/console_listener.py
rci/logic/listeners/execution_listener.py
rci/logic/listeners/input_listener.py
rci/logic/listeners/keyword_listener.py
rci/logic/listeners/log_listener.py
rci/representation/__init__.py
rci/representation/interface.py
rci/representation/sub_window.py
robot_console_improved-0.2.dist-info/METADATA
robot_console_improved-0.2.dist-info/WHEEL
robot_console_improved-0.2.dist-info/entry_points.txt
robot_console_improved-0.2.dist-info/RECORD
