Metadata-Version: 2.3
Name: robot-console-improved
Version: 0.2
Author-email: Inte Vleminckx <inte.vleminckx@qteal.com>
License: (c) Copyright Qteal 2023 - Proprietary software, all rights reserved.
Requires-Python: >=3.10
Requires-Dist: robotframework
Provides-Extra: robot-debug
Requires-Dist: robotframework-debuglibrary; extra == 'robot-debug'
